{
  "required": true,
  "minVersion": "0.8",
  "package": "com.teampotato.redirectionor.mixin",
  "compatibilityLevel": "JAVA_8",
  "refmap": "redirectionor-refmap.json",
  "mixins": [
    "block.AbstractBlockMixin",
    "block.AbstractCoralPlantBlockMixin",
    "block.AbstractFireBlockMixin",
    "block.AbstractPressurePlateBlockMixin",
    "block.BambooBlockMixin",
    "block.BambooSaplingBlockMixin",
    "block.BannerBlockMixin",
    "block.BellBlockMixin",
    "block.BlockMixin",
    "block.BubbleColumnBlockMixin",
    "block.BushBlockMixin",
    "block.CactusBlockMixin",
    "block.CakeBlockMixin",
    "block.CampfireBlockMixin",
    "block.ChorusFlowerBlockMixin",
    "block.ChorusPlantBlockMixin",
    "block.ConcretePowderBlockMixin",
    "block.CoralBlockMixin",
    "block.CoralFinBlockMixin",
    "block.CoralPlantBlockMixin",
    "block.CropsBlockMixin",
    "block.CryingObsidianBlockMixin",
    "block.DetectorRailBlockMixin",
    "block.DoorBlockMixin",
    "block.DoublePlantBlockMixin",
    "block.EndRodBlockMixin",
    "block.FarmlandBlockMixin",
    "block.FireBlockMixin",
    "block.FlowerPotBlockMixin",
    "block.FlowingFluidBlockMixin",
    "block.FrostedIceBlockMixin",
    "block.GrassPathBlockMixin",
    "block.HopperBlockMixin",
    "block.HorizontalFaceBlockMixin",
    "block.HugeMushroomBlockMixin",
    "block.JigsawBlockMixin",
    "block.KelpBlockMixin",
    "block.KelpTopBlockMixin",
    "block.LanternBlockMixin",
    "block.LeavesBlockMixin",
    "block.LecternBlockMixin",
    "block.MagmaBlockMixin",
    "block.MushroomBlockMixin",
    "block.NoteBlockMixin",
    "block.NyliumBlockMixin",
    "block.PistonBlockMixin",
    "block.PistonBlockStructureHelperMixin",
    "block.PistonHeadBlockMixin",
    "block.PortalSizeMixin",
    "block.RedstoneDiodeBlockMixin",
    "block.RedstoneOreBlockMixin",
    "block.RedstoneTorchBlockMixin",
    "block.RedstoneWireBlockMixin",
    "block.ScaffoldingBlockMixin",
    "block.SeaGrassBlockMixin",
    "block.SeaPickleBlockMixin",
    "block.ShulkerBoxBlockMixin",
    "block.SlabBlockMixin",
    "block.SnowBlockMixin",
    "block.SnowyDirtBlockMixin",
    "block.SoulSandBlockMixin",
    "block.SpongeBlockMixin",
    "block.SpreadableSnowyDirtBlockMixin",
    "block.StairsBlockMixin",
    "block.StandingSignBlockMixin",
    "block.StemBlockMixin",
    "block.SugarCaneBlockMixin",
    "block.TallSeaGrassBlockMixin",
    "block.TorchBlockMixin",
    "block.TrapDoorBlockMixin",
    "block.TrappedChestBlockMixin",
    "block.TwistingVinesBlockMixin",
    "block.TwistingVinesTopBlockMixin",
    "block.VineBlockMixin",
    "block.WallBlockMixin",
    "block.WeepingVinesBlockMixin",
    "block.WeepingVinesTopBlockMixin",
    "block.WetSpongeBlockMixin",
    "block.pattern.BlockPatternMixin",
    "command.impl.SpreadPlayersCommandMixin",
    "data.BlockModelProviderMixin",
    "dispenser.ShulkerBoxDispenseBehaviorMixin",
    "enchantment.FrostWalkerEnchantmentMixin",
    "entity.EntityMixin",
    "entity.LivingEntityMixin",
    "entity.ai.goal.WaterAvoidingRandomFlyingGoalMixin",
    "entity.item.FallingBlockEntityMixin",
    "entity.item.HangingEntityMixin",
    "entity.monster.EndermanEntityMixin",
    "entity.monster.EvokerEntityMixin",
    "entity.monster.PlaceBlockGoalMixin",
    "entity.monster.ShulkerEntityMixin",
    "entity.passive.StriderEntityMixin",
    "entity.passive.horse.AbstractHorseEntityMixin",
    "entity.projectile.ShulkerBulletEntityMixin",
    "fluid.FlowingFluidMixin",
    "fluid.LavaFluidMixin",
    "fluid.WaterFluidMixin",
    "item.ArmorStandItemMixin",
    "item.DirectionalPlaceContextMixin",
    "item.FilledMapItemMixin",
    "item.HoeItemMixin",
    "item.ScaffoldingItemMixin",
    "item.ShovelItemMixin",
    "item.SpawnEggItemMixin",
    "item.WallOrFloorItemMixin",
    "network.play.ServerPlayNetHandlerMixin",
    "pathfinding.SwimNodeProcessorMixin",
    "pathfinding.WalkAndSwimNodeProcessorMixin",
    "state.DirectionPropertyMixin",
    "tileentity.AbstractFurnaceTileEntityMixin",
    "tileentity.BrewingStandTileEntityMixin",
    "tileentity.EndGatewayTileEntityMixin",
    "tileentity.EndPortalTileEntityMixin",
    "tileentity.HopperTileEntityMixin",
    "tileentity.ShulkerBoxTileEntityMixin",
    "util.TransportationHelperMixin",
    "util.math.AxisAlignedBBMixin",
    "util.math.BlockPosMixin",
    "util.math.vector.OrientationMixin",
    "util.math.vector.Vector3iMixin",
    "util.palette.UpgradeDataMixin",
    "world.TeleporterMixin",
    "world.WorldMixin",
    "world.gen.blockplacer.ColumnBlockPlacerMixin",
    "world.gen.carver.WorldCarverMixin",
    "world.gen.feature.AbstractBigMushroomFeatureMixin",
    "world.gen.feature.BambooFeatureMixin",
    "world.gen.feature.BasaltColumnFeatureMixin",
    "world.gen.feature.BasaltDeltasStructureMixin",
    "world.gen.feature.BasaltPillarFeatureMixin",
    "world.gen.feature.BlockPileFeatureMixin",
    "world.gen.feature.BlueIceFeatureMixin",
    "world.gen.feature.CoralClawFeatureMixin",
    "world.gen.feature.CoralMushroomFeatureMixin",
    "world.gen.feature.CoralTreeFeatureMixin",
    "world.gen.feature.GlowstoneBlobFeatureMixin",
    "world.gen.feature.HugeFungusFeatureMixin",
    "world.gen.feature.IceAndSnowFeatureMixin",
    "world.gen.feature.NoExposedOreFeatureMixin",
    "world.gen.feature.SkyLightStorageMixin",
    "world.gen.feature.TreeFeatureMixin",
    "world.gen.feature.TwistingVineFeatureMixin",
    "world.gen.feature.VinesFeatureMixin",
    "world.gen.feature.WeepingVineFeatureMixin",
    "world.gen.feature.jigsaw.FeatureJigsawPieceMixin",
    "world.gen.feature.structure.BuriedTreasureMixin",
    "world.gen.feature.structure.DoubleXRoomMixin",
    "world.gen.feature.structure.DoubleXYRoomMixin",
    "world.gen.feature.structure.DoubleYRoomMixin",
    "world.gen.feature.structure.DoubleYZRoomMixin",
    "world.gen.feature.structure.DoubleZRoomMixin",
    "world.gen.feature.structure.FitSimpleRoomTopHelperMixin",
    "world.gen.feature.structure.JunglePyramidPieceMixin",
    "world.gen.feature.structure.MonumentBuildingMixin",
    "world.gen.feature.structure.NetherackBlobReplacementStructureMixin",
    "world.gen.feature.structure.NetherFossilStructureMixin",
    "world.gen.feature.structure.RuinedPortalPieceMixin",
    "world.gen.feature.structure.SimpleRoomMixin",
    "world.gen.feature.structure.SimpleTopRoomMixin",
    "world.gen.feature.structure.WoodlandMansionPiecesMixin",
    "world.gen.feature.structure.XYDoubleRoomFitHelperMixin",
    "world.gen.feature.structure.YDoubleRoomFitHelperMixin",
    "world.gen.feature.structure.YZDoubleRoomFitHelperMixin",
    "world.gen.surfacebuilders.ValleySurfaceBuilderMixin",
    "world.lighting.SkyLightEngineMixin",
    "world.lighting.SkyLightStorageMixin",
    "world.spawner.WorldEntitySpawnerMixin"
  ],
  "client": [
    "client.MinecraftMixin",
    "client.entity.player.ClientPlayerEntityMixin",
    "client.multiplayer.PlayerControllerMixin",
    "client.particle.ParticleManagerMixin",
    "client.renderer.BlockModelRendererMixin",
    "client.renderer.FluidBlockRendererMixin",
    "client.renderer.chunk.ChunkRenderDispatcherMixin",
    "client.renderer.chunk.SetVisibilityMixin",
    "client.renderer.chunk.VisGraphMixin",
    "client.renderer.debug.SolidFaceDebugRendererMixin",
    "client.renderer.model.FaceBakeryMixin",
    "client.renderer.model.ModelRendererMixin",
    "client.renderer.model.SimpleBakedModelMixin",
    "client.renderer.tileentity.EndPortalTileEntityRendererMixin",
    "client.renderer.tileentity.ShulkerBoxTileEntityRendererMixin"
  ]
}